agentdk/__init__.py
agentdk/exceptions.py
agentdk/agent/__init__.py
agentdk/agent/agent_interface.py
agentdk/agent/app_utils.py
agentdk/agent/base_app.py
agentdk/agent/factory.py
agentdk/agent/session_manager.py
agentdk/builder/__init__.py
agentdk/builder/agent_builder.py
agentdk/cli/__init__.py
agentdk/cli/agent_loader.py
agentdk/cli/interactive.py
agentdk/cli/main.py
agentdk/core/__init__.py
agentdk/core/logging_config.py
agentdk/core/mcp_load.py
agentdk/core/persistent_mcp.py
agentdk/memory/__init__.py
agentdk/memory/base.py
agentdk/memory/episodic_memory.py
agentdk/memory/factual_memory.py
agentdk/memory/memory_aware_agent.py
agentdk/memory/memory_manager.py
agentdk/memory/memory_tools.py
agentdk/memory/working_memory.py
agentdk/tui/__init__.py
agentdk/tui/app.py
agentdk/tui/layouts/__init__.py
agentdk/tui/screens/__init__.py
agentdk/tui/screens/chat_screen.py
agentdk/tui/themes/__init__.py
agentdk/tui/themes/agentdk_theme.py
agentdk/tui/widgets/__init__.py
agentdk/tui/widgets/chat_panel.py
agentdk/tui/widgets/multiline_input.py
agentdk/utils/utils.py
agentdk-0.3.0.dist-info/METADATA
agentdk-0.3.0.dist-info/WHEEL
agentdk-0.3.0.dist-info/entry_points.txt
agentdk-0.3.0.dist-info/licenses/LICENSE
agentdk-0.3.0.dist-info/RECORD
