Metadata-Version: 2.4
Name: agentdk
Version: 0.3.0
Summary: Agent Development Kit for building intelligent agents with LangGraph and MCP integration, Support Agent Async in jupyter notebook/IPython
Project-URL: Homepage, https://github.com/breadpowder/agentdk
Project-URL: Bug Tracker, https://github.com/breadpowder/agentdk/issues
Author-email: Zineng Yuan <zineng.yuan01@gmail.com>
License: MIT
License-File: LICENSE
Keywords: agents,ai,automation,langgraph,llm,mcp,multi-agent
Classifier: Development Status :: 4 - Beta
Classifier: Intended Audience :: Developers
Classifier: License :: OSI Approved :: MIT License
Classifier: Operating System :: OS Independent
Classifier: Programming Language :: Python :: 3
Classifier: Programming Language :: Python :: 3.11
Classifier: Programming Language :: Python :: 3.12
Classifier: Topic :: Scientific/Engineering :: Artificial Intelligence
Classifier: Topic :: Software Development :: Libraries :: Python Modules
Requires-Python: >=3.11
Requires-Dist: click>=8.0.0
Requires-Dist: langchain-core>=0.3.63
Requires-Dist: langchain-mcp-adapters>=0.1.7
Requires-Dist: langgraph-supervisor>=0.0.27
Requires-Dist: langgraph>=0.4.8
Requires-Dist: mcp[cli]>=1.8.1
Requires-Dist: mem0ai>=0.1.111
Requires-Dist: nest-asyncio<2.0.0,>=1.6.0
Requires-Dist: pydantic>=2.11.5
Requires-Dist: python-dotenv>=1.0.0
Requires-Dist: pyyaml>=6.0.2
Requires-Dist: sqlparse<1.0.0,>=0.4.4
Provides-Extra: all
Requires-Dist: black>=24.0.0; extra == 'all'
Requires-Dist: isort>=5.13.0; extra == 'all'
Requires-Dist: langchain-anthropic>=0.1.0; extra == 'all'
Requires-Dist: langchain-openai>=0.3.24; extra == 'all'
Requires-Dist: mypy>=1.8.0; extra == 'all'
Requires-Dist: pytest-asyncio>=0.21.0; extra == 'all'
Requires-Dist: pytest-cov>=5.0.0; extra == 'all'
Requires-Dist: pytest>=8.4.1; extra == 'all'
Requires-Dist: toml>=0.10.2; extra == 'all'
Provides-Extra: anthropic
Requires-Dist: langchain-anthropic>=0.1.0; extra == 'anthropic'
Provides-Extra: cli
Requires-Dist: langchain-anthropic>=0.1.0; extra == 'cli'
Requires-Dist: langchain-openai>=0.3.24; extra == 'cli'
Provides-Extra: dev
Requires-Dist: black>=24.0.0; extra == 'dev'
Requires-Dist: isort>=5.13.0; extra == 'dev'
Requires-Dist: langchain-openai>=0.3.24; extra == 'dev'
Requires-Dist: mypy>=1.8.0; extra == 'dev'
Requires-Dist: pytest-asyncio>=0.21.0; extra == 'dev'
Requires-Dist: pytest-cov>=5.0.0; extra == 'dev'
Requires-Dist: pytest>=8.4.1; extra == 'dev'
Requires-Dist: toml>=0.10.2; extra == 'dev'
Provides-Extra: openai
Requires-Dist: langchain-openai>=0.3.24; extra == 'openai'
